ovos_skill_icanhazdadjokes/LICENSE
ovos_skill_icanhazdadjokes/MANIFEST.in
ovos_skill_icanhazdadjokes/README.md
ovos_skill_icanhazdadjokes/__init__.py
ovos_skill_icanhazdadjokes/requirements-dev.txt
ovos_skill_icanhazdadjokes/requirements.txt
ovos_skill_icanhazdadjokes/version.py
ovos_skill_icanhazdadjokes/locale/ca-es/ChuckNorris.voc
ovos_skill_icanhazdadjokes/locale/ca-es/Dad.voc
ovos_skill_icanhazdadjokes/locale/ca-es/Programmer.voc
ovos_skill_icanhazdadjokes/locale/ca-es/Pun.voc
ovos_skill_icanhazdadjokes/locale/ca-es/joke.intent
ovos_skill_icanhazdadjokes/locale/ca-es/no_joke.dialog
ovos_skill_icanhazdadjokes/locale/ca-es/search_joke.intent
ovos_skill_icanhazdadjokes/locale/ca-es/skill.json
ovos_skill_icanhazdadjokes/locale/cs/chuck_norris_jokes.dialog
ovos_skill_icanhazdadjokes/locale/cs/dev_jokes.dialog
ovos_skill_icanhazdadjokes/locale/da-dk/joke.intent
ovos_skill_icanhazdadjokes/locale/da-dk/no_joke.dialog
ovos_skill_icanhazdadjokes/locale/da-dk/search_joke.intent
ovos_skill_icanhazdadjokes/locale/da-dk/skill.json
ovos_skill_icanhazdadjokes/locale/de-de/ChuckNorris.voc
ovos_skill_icanhazdadjokes/locale/de-de/Dad.voc
ovos_skill_icanhazdadjokes/locale/de-de/Programmer.voc
ovos_skill_icanhazdadjokes/locale/de-de/Pun.voc
ovos_skill_icanhazdadjokes/locale/de-de/chuck_norris_jokes.dialog
ovos_skill_icanhazdadjokes/locale/de-de/dad_jokes.dialog
ovos_skill_icanhazdadjokes/locale/de-de/dev_jokes.dialog
ovos_skill_icanhazdadjokes/locale/de-de/general_jokes.dialog
ovos_skill_icanhazdadjokes/locale/de-de/joke.intent
ovos_skill_icanhazdadjokes/locale/de-de/no_joke.dialog
ovos_skill_icanhazdadjokes/locale/de-de/search_joke.intent
ovos_skill_icanhazdadjokes/locale/de-de/skill.json
ovos_skill_icanhazdadjokes/locale/en-us/ChuckNorris.voc
ovos_skill_icanhazdadjokes/locale/en-us/Dad.voc
ovos_skill_icanhazdadjokes/locale/en-us/Programmer.voc
ovos_skill_icanhazdadjokes/locale/en-us/Pun.voc
ovos_skill_icanhazdadjokes/locale/en-us/chuck_norris_jokes.dialog
ovos_skill_icanhazdadjokes/ovos_skill_icanhazdadjokes.egg-info/PKG-INFO
ovos_skill_icanhazdadjokes/ovos_skill_icanhazdadjokes.egg-info/SOURCES.txt
ovos_skill_icanhazdadjokes/ovos_skill_icanhazdadjokes.egg-info/dependency_links.txt
ovos_skill_icanhazdadjokes/ovos_skill_icanhazdadjokes.egg-info/entry_points.txt
ovos_skill_icanhazdadjokes/ovos_skill_icanhazdadjokes.egg-info/requires.txt
ovos_skill_icanhazdadjokes/ovos_skill_icanhazdadjokes.egg-info/top_level.txt
ovos_skill_icanhazdadjokes-0.3.7.dist-info/LICENSE
ovos_skill_icanhazdadjokes-0.3.7.dist-info/METADATA
ovos_skill_icanhazdadjokes-0.3.7.dist-info/WHEEL
ovos_skill_icanhazdadjokes-0.3.7.dist-info/entry_points.txt
ovos_skill_icanhazdadjokes-0.3.7.dist-info/top_level.txt
ovos_skill_icanhazdadjokes-0.3.7.dist-info/RECORD
