Metadata-Version: 2.1
Name: ovos-skill-icanhazdadjokes
Version: 0.3.7
Summary: OVOS jokes skill plugin
Home-page: https://github.com/OpenVoiceOS/ovos-skill-icanhazdadjokes
Author: OpenVoiceOS
Author-email: jarbasai@mailfence.com
License: Apache-2.0
Keywords: ovos skill plugin
License-File: LICENSE
Requires-Dist: ovos-workshop<8.0.0,>=0.0.15
Requires-Dist: ovos-utils<1.0.0,>=0.0.38
